prism_embedder/__init__.py
prism_embedder/aggregate.py
prism_embedder/embed.py
prism_embedder/main.py
prism_embedder/tiling.py
prism_embedder/configs/__init__.py
prism_embedder/data/__init__.py
prism_embedder/data/dataset.py
prism_embedder/distributed/__init__.py
prism_embedder/models/__init__.py
prism_embedder/models/models.py
prism_embedder/models/vision_transformer.py
prism_embedder/models/prism/__init__.py
prism_embedder/models/prism/biogpt.py
prism_embedder/models/prism/biogpt_hf.py
prism_embedder/models/prism/configuring_prism.py
prism_embedder/models/prism/memory_test.py
prism_embedder/models/prism/modeling_prism.py
prism_embedder/models/prism/perceiver.py
prism_embedder/utils/__init__.py
prism_embedder/utils/config.py
prism_embedder/utils/log_utils.py
prism_embedder/utils/utils.py
prism_embedder/wsi/__init__.py
prism_embedder/wsi/utils.py
prism_embedder/wsi/wsi.py
prism_embedder-1.1.1.dist-info/licenses/LICENSE
prism_embedder-1.1.1.dist-info/METADATA
prism_embedder-1.1.1.dist-info/WHEEL
prism_embedder-1.1.1.dist-info/entry_points.txt
prism_embedder-1.1.1.dist-info/top_level.txt
prism_embedder-1.1.1.dist-info/RECORD
